jsonvcs.py
setup.py
jsonvcs.egg-info/PKG-INFO
jsonvcs.egg-info/SOURCES.txt
jsonvcs.egg-info/dependency_links.txt
jsonvcs.egg-info/requires.txt
jsonvcs.egg-info/top_level.txt