Metadata-Version: 1.0
Name: jsonvcs
Version: 0.0.1
Summary: version control for structured documents
Home-page: https://github.com/slang800/jsonvcs
Author: Sean Lang
Author-email: slang800@gmail.com
License: LICENSE
Platform: UNKNOWN
